pyransac/__init__.py
pyransac/base.py
pyransac/line2d.py
pyransac/ransac.py
pyransac-1.1.3.dist-info/LICENSE
pyransac-1.1.3.dist-info/METADATA
pyransac-1.1.3.dist-info/WHEEL
pyransac-1.1.3.dist-info/top_level.txt
pyransac-1.1.3.dist-info/RECORD
