Metadata-Version: 2.1
Name: pyransac
Version: 1.1.3
Summary: A general random sample consensus (RANSAC) package
Home-page: https://github.com/adamlm/pyransac
Author: Adam Morrissett
Author-email: me@adamlm.com
License: UNKNOWN
Keywords: random sample consensus ransac
Platform: UNKNOWN
Classifier: Programming Language :: Python :: 3
Classifier: License :: OSI Approved :: MIT License
Classifier: Operating System :: OS Independent
Requires-Python: >=3.7
